breiman_cart/__init__.py
breiman_cart/breiman_cart.py
breiman_cart/node.py
breiman_cart/pruning.py
breiman_cart/splitter.py
breiman_cart/tree.py
breiman_cart-0.2.1.dist-info/licenses/LICENSE
breiman_cart-0.2.1.dist-info/METADATA
breiman_cart-0.2.1.dist-info/WHEEL
breiman_cart-0.2.1.dist-info/top_level.txt
breiman_cart-0.2.1.dist-info/RECORD
