Metadata-Version: 2.4
Name: breiman-cart
Version: 0.2.1
Summary: Implementation of Breiman's CART (Classification and Regression Trees) algorithm
Author-email: Adam Khald <adamkhald@outlook.com>
License: MIT
Project-URL: Homepage, https://github.com/Adamkhald/breiman-cart
Project-URL: Repository, https://github.com/Adamkhald/breiman-cart
Project-URL: Documentation, https://github.com/Adamkhald/breiman-cart#readme
Project-URL: Issues, https://github.com/Adamkhald/breiman-cart/issues
Keywords: cart,decision-tree,machine-learning,breiman
Classifier: Development Status :: 4 - Beta
Classifier: Intended Audience :: Developers
Classifier: Intended Audience :: Science/Research
Classifier: License :: OSI Approved :: MIT License
Classifier: Programming Language :: Python :: 3
Classifier: Programming Language :: Python :: 3.8
Classifier: Programming Language :: Python :: 3.9
Classifier: Programming Language :: Python :: 3.10
Classifier: Programming Language :: Python :: 3.11
Classifier: Programming Language :: Python :: 3.12
Classifier: Topic :: Scientific/Engineering :: Artificial Intelligence
Classifier: Operating System :: OS Independent
Requires-Python: >=3.8
License-File: LICENSE
Requires-Dist: numpy>=1.20.0
Requires-Dist: pandas>=1.3.0
Provides-Extra: dev
Requires-Dist: pytest>=7.0.0; extra == "dev"
Requires-Dist: build>=0.10.0; extra == "dev"
Requires-Dist: twine>=4.0.0; extra == "dev"
Dynamic: license-file
